coordinated.py
dojo.py
fem.py
physicsrl.py
physicsrl-1.0.0.dist-info/METADATA
physicsrl-1.0.0.dist-info/WHEEL
physicsrl-1.0.0.dist-info/top_level.txt
physicsrl-1.0.0.dist-info/RECORD
