Metadata-Version: 2.1
Name: physicsrl
Version: 1.0.0
Summary: A package for reinforcement learning in physics simulations
Author: Andrea Zanin
Classifier: Programming Language :: Python :: 3
Classifier: License :: OSI Approved :: MIT License
Classifier: Operating System :: OS Independent
Requires-Python: >=3.6
Requires-Dist: tf-agents ==0.17.0
Requires-Dist: tensorflow ==2.13.0
Requires-Dist: numpy ==1.24.0
Requires-Dist: imageio ==2.4.0
Requires-Dist: jupyterlab
Requires-Dist: matplotlib
Requires-Dist: pyglet
Requires-Dist: pyvirtualdisplay
